GeoCal/Geometry.py
GeoCal/LocDisDir.py
GeoCal/__init__.py
GeoData/POI.py
GeoData/POIException.py
GeoData/__init__.py
example/__init__.py
example/test_poi.py
geo_tools_py-1.0.1.dist-info/METADATA
geo_tools_py-1.0.1.dist-info/WHEEL
geo_tools_py-1.0.1.dist-info/top_level.txt
geo_tools_py-1.0.1.dist-info/RECORD
