Metadata-Version: 2.1
Name: geo-tools-py
Version: 1.0.1
Summary: Geo SDK for python
Home-page: http://datahub.wtf
Author: caidong
Author-email: zhucaidong@aliyun.com
License: Apache License 2.0
Platform: UNKNOWN
Requires-Python: >=2.7
Requires-Dist: requests
